modal_for_noobs/__init__.py
modal_for_noobs/auth_manager.py
modal_for_noobs/cli.py
modal_for_noobs/cli_enhanced.py
modal_for_noobs/complete_dashboard.py
modal_for_noobs/config.py
modal_for_noobs/config_loader.py
modal_for_noobs/dashboard.py
modal_for_noobs/dashboard_auth.py
modal_for_noobs/easy-modal-complete.md
modal_for_noobs/easy_auth.py
modal_for_noobs/enhanced_dashboard.py
modal_for_noobs/github_api.py
modal_for_noobs/huggingface.py
modal_for_noobs/logging_config.py
modal_for_noobs/modal_deploy.py
modal_for_noobs/modal_github_api.py
modal_for_noobs/modal_modal_github_api.py
modal_for_noobs/template_generator.py
modal_for_noobs/cli_helpers/__init__.py
modal_for_noobs/cli_helpers/auth_helper.py
modal_for_noobs/cli_helpers/common.py
modal_for_noobs/cli_helpers/config_helper.py
modal_for_noobs/cli_helpers/logs_helper.py
modal_for_noobs/config/base_packages.yml
modal_for_noobs/config/deployment_examples.yml
modal_for_noobs/config/modal_marketing.yml
modal_for_noobs/examples/modal_modal_simple_hello.py
modal_for_noobs/examples/modal_simple_hello.py
modal_for_noobs/examples/modal_test_gradio_app.py
modal_for_noobs/examples/modal_ultimate_green_app.py
modal_for_noobs/examples/ultimate_green_app.py
modal_for_noobs/templates/__init__.py
modal_for_noobs/templates/dashboard.py
modal_for_noobs/templates/deployment.py
modal_for_noobs/templates/template_constants.py
modal_for_noobs/templates/gradio-jupyter/deployment_template.py
modal_for_noobs/templates/gradio-jupyter/pyproject.toml
modal_for_noobs/templates/jinja2/base_deployment.j2
modal_for_noobs/templates/jinja2/fastapi_wrapper.j2
modal_for_noobs/templates/jinja2/gradio-jupyter_deployment.j2
modal_for_noobs/templates/jinja2/gradio_wrapper.j2
modal_for_noobs/templates/jinja2/marimo_deployment.j2
modal_for_noobs/templates/jinja2/minimum_deployment.j2
modal_for_noobs/templates/jinja2/optimized_deployment.j2
modal_for_noobs/templates/marimo/deployment_template.py
modal_for_noobs/templates/marimo/pyproject.toml
modal_for_noobs-0.3.2.dist-info/METADATA
modal_for_noobs-0.3.2.dist-info/WHEEL
modal_for_noobs-0.3.2.dist-info/entry_points.txt
modal_for_noobs-0.3.2.dist-info/licenses/LICENSE.jinja
modal_for_noobs-0.3.2.dist-info/RECORD
