Metadata-Version: 2.4
Name: modal-for-noobs
Version: 0.3.2
Summary: 🚀 Async-first, idiot-proof Gradio deployment CLI for Modal
Project-URL: Repository, https://github.com/arthrod/modal-for-noobs
Project-URL: Issues, https://github.com/arthrod/modal-for-noobs/issues
Author-email: Arthur Souza Rodrigues <arthrod@umich.edu>
License: MIT
License-File: LICENSE.jinja
Requires-Python: >=3.11
Requires-Dist: click>=8.1.7
Requires-Dist: fastapi>=0.115.12
Requires-Dist: gradio>=5.33.0
Requires-Dist: httpx>=0.27.2
Requires-Dist: huggingface-hub>=0.32.4
Requires-Dist: jinja2>=3.1.0
Requires-Dist: loguru>=0.7.2
Requires-Dist: markdown2>=2.4.0
Requires-Dist: modal>=1.0.3
Requires-Dist: python-dotenv>=1.0.0
Requires-Dist: python-slugify>=8.0.0
Requires-Dist: pyyaml>=6.0.2
Requires-Dist: questionary>=2.0.0
Requires-Dist: rich>=14.0.0
Requires-Dist: security==1.3.1
Requires-Dist: toml>=0.10.2
Requires-Dist: typer>=0.16.0
Requires-Dist: typing-inspection>=0.4.1
Requires-Dist: unkey-py>=0.6.2
Requires-Dist: uvicorn>=0.34.3
Requires-Dist: uvloop>=0.21.0
